setup.py
ytsingleton/__init__.py
ytsingleton/singleton.py
ytsingleton.egg-info/PKG-INFO
ytsingleton.egg-info/SOURCES.txt
ytsingleton.egg-info/dependency_links.txt
ytsingleton.egg-info/not-zip-safe
ytsingleton.egg-info/top_level.txt