Metadata-Version: 1.0
Name: ytsingleton
Version: 0.1
Summary: Prevent your script from running in parallel.
Home-page: https://github.com/sunzhongwei/ytsingleton
Author: Zhongwei Sun
Author-email: zhongwei.sun2008@gmail.com
License: MIT
Platform: UNKNOWN
